alsolib/__init__.py
alsolib/api.py
alsolib/hychat.py
alsolib/qq.py
alsolib/xes.py
lsolib-3.4.20221117.dist-info/METADATA
lsolib-3.4.20221117.dist-info/WHEEL
lsolib-3.4.20221117.dist-info/top_level.txt
lsolib-3.4.20221117.dist-info/RECORD
