Metadata-Version: 2.1
Name: lsolib
Version: 3.4.20221117
Summary: 🔥火焰爱搜🔥学而思专用库🔥
Home-page: UNKNOWN
Author: asunc
Author-email: 3182305655@qq.com
Maintainer: asunc
Maintainer-email: 3182305655@qq.com
License: BSD License
Platform: all
Classifier: Development Status :: 4 - Beta
Classifier: Operating System :: OS Independent
Classifier: Intended Audience :: Developers
Classifier: License :: OSI Approved :: BSD License
Classifier: Programming Language :: Python :: 3
Classifier: Topic :: Software Development :: Libraries
Requires-Dist: requests
Requires-Dist: pygame
Requires-Dist: zmail
Requires-Dist: pillow
Requires-Dist: numpy
Requires-Dist: cefpython3
Requires-Dist: huoyanlib
Requires-Dist: xingyunlib
